{
  "id": "haval-h6",
  "brand_id": "haval",
  "name_cn": "哈弗H6",
  "name_en": "Haval H6",
  "intro": "哈弗H6是长城汽车旗下哈弗品牌的紧凑型SUV，连续多年蝉联中国SUV销量冠军，是中国市场最畅销的SUV车型之一，以高性价比和可靠性著称。",
  "category": "suv",
  "generations": [
    {
      "id": "haval-h6-gen3",
      "name": "第三代",
      "year_start": 2020,
      "variants": [
        {
          "id": "haval-h6-2023-1.5t",
          "name": "1.5T 自动冠军版",
          "year": 2023,
          "body_type": "SUV",
          "powertrain": "petrol",
          "transmission": "7挡双离合",
          "drivetrain": "fwd",
          "specs": {
            "length": 4653,
            "width": 1886,
            "height": 1730,
            "wheelbase": 2738,
            "weight": 1530,
            "power": 150,
            "torque": 233,
            "zero_to_hundred": 9.7,
            "top_speed": 185
          },
          "price_range": "9.89-15.70万元"
        }
      ]
    }
  ],
  "image": "/series/haval-h6.jpg",
  "gallery": [
    "/series/haval-h6.jpg",
    "/series/haval-h6-2.jpg",
    "/series/haval-h6-3.jpg"
  ]
}
